local_hive/__init__.py
local_hive/__main__.py
local_hive/exceptions.py
local_hive/loader.py
local_hive/permissions.py
local_hive/protocol.py
local_hive/service.py
local_hive/version.py
hivemind_local-0.0.3a5.dist-info/METADATA
hivemind_local-0.0.3a5.dist-info/WHEEL
hivemind_local-0.0.3a5.dist-info/top_level.txt
hivemind_local-0.0.3a5.dist-info/RECORD
